Verilog/VerilogBM-125-254.v
/*
	Title            		  :- Automatic Door Controller
	register No      		  :- 16CO125 - 16CO254
	Abstract         		  :- Automatic Door Controller
	Functionalities  		  :- 1.If door is closed and person approaches it opens.
                        		 2.After some time it completely opens and if no one is present it closes.
								 3.If the door is closed then it can be locked that will make it bolted.
								 4.If the door is locked and someone approaches then also it does not open.
								 5.3 failed attempts to manually open a lock door triggers the alarm.
								 6.If door is closing and door resistance(person present) in door frame comes
						  		  it opens.
	Brief Description on code:-  In the code main module calls the door module twice, one of them replicates right door other
	                             left door. Counter module is called with Manual open as clock,enable when door is bolted,the alarm buzzes after three failed manual attempts to open door,
								 only setting reset as 1 can then stop the alarm. 
								 Door module calls the nextstate module to get the nextstate value.Nextstate value is calculated 
								 with the help of case statement and different decision making statements. Simlarly output 
								 module is also called to get the desired output of motors.
*/

`include "Verilog-125-254.v"
module VerilogBM_125_254(output bt,
			output[1:0] yt1,// Next State
			output 	r2m,	// right to Middle rotation motor
					m2r,	// Middle to right rotation motor
					l2m,	// left to Middle rotation motor
					m2l,	// Middle to left rotation motor
					alarm,	// Alarm
			input 	pa,		// Person Approaching
					pp,		// Person Present between doors
					mo,		// Manual Opening
					r,		// right limit
					l,		// left limit
					M,		// Middle limit
					lk,		// lock
					clk,	// Clock
					reset,	// reset
			inout[1:0] yt);	// Present State
	wire t1,t2;				// Output of 2-bit counter
	
	// left Door Circuit
	door left_door(bt,yt1,r2m,m2r,pa,pp,mo,r,M,lk,clk,reset,yt);
	// right Door Circuit
	door right_door(bt,yt1,l2m,m2l,pa,pp,mo,l,M,lk,clk,reset,yt);
	// Counter to count Manual open tries when the door is locked
	counter f7(mo,reset,bt,t1,t2);
	// Alarm triggers when 3 times manual opening is tried when door is locked
	and (alarm,t1,t2);

endmodule





/*Door module it stores the current state of door in memory and then 
calculates nextstate and output value*/


module door(output bt,
			output[1:0] yt1,ws
			output 	r2l,
					l2r,
			input 	pa,
					pp,
					mo,
					r,
					l,
					lk,
					clk,
					reset,
			inout[1:0] yt);

	nextstate f3(yt,yt1,pa,pp,mo,r,l,lk,clk,reset);
	output_   f4 (bt,r2l,l2r,pa,pp,mo,r,l,yt,lk,clk,reset);

endmodule


/*Nextstate module does nextstate vector assignments using present state
and inputs, it is based on data flow modelling*/

module nextstate(output reg[1:0] yt,
				 			 yt1,
				 input 		 pa,
				 			 pp,
				 			 mo,
				 			 r,
				 			 l,
				 			 lk,
				 			 clk,
				 			 reset);
	
	always @(posedge clk) 
	begin
		// Set initial states to 00
		if(reset)
			begin
				yt=2'b00;
				yt1=2'b00;		
			end
		else
			begin
				// Different States for Behavorial modelling
				case (yt)
					2'b00: 			// Closed State
						begin
							if(lk==1'b1)			// If locked, then next state should be closed
								begin
									yt1[0]=0;
									yt1[1]=0;
								end
							else if(((~lk)&(pa|pp|mo))==1'b1)  // If not lock and any external sensor detected, then go to opening
								begin
									yt1[0]=1;
									yt1[1]=0;
								end
						end
					2'b01: 			// Opening State
						begin
							if(r==1'b1 & l==1'b0)	// If door is open, go to opened state
								begin
									yt1[0]=1;
									yt1[1]=1;
								end
							else if(r==0)			// Else stay in opening
								begin
									yt1[0]=1;
									yt1[1]=0;
								end
						end
					2'b11: 			// Opened State
						begin
							if((pa | pp | mo) & r)	// If external sensors detected, stay in opened state
								begin
									yt1[0]=1;
									yt1[1]=1;
								end
							else if(((~pa)&(~pp)&(~mo))==1'b1 & (r)==1'b1)    // Else go to closing state
								begin
									yt1[0]=0;
									yt1[1]=1;

								end
						end
					2'b10: 			// Closing State
						begin
							if(((~l)&(~pa)&(~pp)&(~mo))==1'b1)		// If no external outputs detected, stay in closing state until closed
								begin
									yt1[0]=0;
									yt1[1]=1;
								end
							else if((l&(~pa)&(~pp)&(~mo))==1'b1)	// If closed, go to closed state
								begin
									yt1[0]=0;
									yt1[1]=0;
								end
							else if((pa|pp|mo)==1'b1)				// If external output detected, go to opening state
								begin
									yt1[0]=1;
									yt1[1]=0;
								end
						end
				endcase
				yt<=yt1;		// NextState will now be the present state
			end
		end
endmodule

/*Output module assigns output variable depending on present state value
and other inputs*/

module output_(output reg bt,
			   			  r2l,
			     		  l2r,
			   input 	  pa,
			   			  pp,
			   			  mo,
			   			  r,
			   			  l,
			   input[1:0] yt,
			   input	  lk,
			   			  clk,
			   			  reset);
	
	always @(posedge clk) 
		begin
			// Set initial states to 0
			if(reset)
				begin
					bt=0;
					r2l=0;
					l2r=0;
				end
			else
				begin
					case (yt)
						2'b00: 			// Closed State
							begin
								if(lk==1'b1)  							//If lock is 1 then the output is as follows
									begin	
										bt=1;
										r2l=0;
										l2r=0;
									end
								else if(((~lk)&(pa|pp|mo))==1'b1)     	//If lock is opened and a sensor is detected then motor turns to open door
									begin
										bt=0;
										r2l=0;
										l2r=1;
									end
							end
						2'b01: 			// Opening State
							begin
								if(r==1'b1 & l==1'b0)        			//If right limit is 1 (door opened) and left limit is 0 then motor is stopped
									begin
										bt=0;
										r2l=0;
										l2r=0;
									end
								else if(r==0)              				//If right limit is 0 (door closed) then motor should go from left to right
									begin
										bt=0;
										r2l=0;
										l2r=1;
									end
							end
						2'b11: 			// Opened State
							begin
								if((pa | pp | mo) & r)					// If external outputs detected, then motor shouldn't change state
									begin
										bt=0;
										r2l=0;
										l2r=0;
									end
								else if(((~pa)&(~pp)&(~mo))==1'b1 & (r)==1'b1)		// If external outputs not detected, then motor should go from right to left
									begin
										bt=0;
										r2l=1;
										l2r=0;
									end
							end
						2'b10: 			// Closing State
							begin
								if(((~l)&(~pa)&(~pp)&(~mo))==1'b1)					// If external outputs not detected, then motor should continue going from right to left
									begin
										bt=0;
										r2l=1;
										l2r=0;
									end
								else if((l&(~pa)&(~pp)&(~mo))==1'b1)				// If external outputs not detected, and door completely closed, motor shouldn't rotate
									begin
										bt=0;
										r2l=0;
										l2r=0;
									end
								else if((pa|pp|mo)==1'b1)							// If external outputs detected, motor should rotate from left to right
									begin
										bt=0;
										r2l=0;
										l2r=1;
									end
							end
					endcase	
				end
			end
endmodule


/*
Counter module counts upto 3 to generate the output for alarm, a preset is set for the counter to remain at 3 once the output is 11
, a reset is set for the counter to become 0 upon making that input high. 
*/

module counter(input      clk,				// clock
			   		      reset,			// reset, serves the purpose to reset the circuit
			        	  enable,			// enable here is the lock of the door
			   output reg a0,				// output 0 of 2bit counter
			   			  a1				// output 1 of 2bit counter
			  );
	
	reg preset;
	initial begin
		preset=1'b0;		// Set preset = 0
	end
	always@(posedge clk or reset)
		begin
			if(reset==1'b0)											// If reset is 0, go to counter
				begin
					if(enable)										// If enable(locked) isn't high, we don't want to increase the counter
						begin	
							if(~preset)								// Count until preset becomes one
								begin
									if(a0 & a1)
										begin
											preset<=1'b1;			// if 3 is output, set preset=1
										end
									else
										begin
											a0<=(1^a0);				// Counter equations
											a1<=(a0^a1);			
										end
								end
							else
								begin
									a0=1'b1;
									a1=1'b1;
								end
						end
				end
			else													// Else set the count to 0
				begin
					a0=1'b0;
					a1=1'b0;
				end
		end
endmodule

Verilog/Verilog-125-254.v
/*
	Title            		  :- Automatic Door Controller
	register No      		  :- 16CO125 - 16CO254
	Abstract         		  :- Automatic Door Controller
	Functionalities  		  :- 1.If door is closed and person approaches it opens.
                        		 2.After some time it completely opens and if no one is present it closes.
								 3.If the door is closed then it can be locked that will make it bolted.
								 4.If the door is locked and someone approaches then also it does not open.
								 5.3 failed attempts to manually open a lock door triggers the alarm.
								 6.If door is closing and door resistance(person present) in door frame comes
						  		  it opens.
	Brief Description on code:-  All the functionalities of the project are one by one at every positive edge of clock pulse
	                             are fed to the respective top level files. Gtkwave is generated to verify the result.
*/

`timescale 1ns/1ps
module Verilog_125_254;
	wire bt,				// Bolted
		r2m,				// right to middle motor
		m2r,				// middle to right motor
		m2l,				// middle to left motor
		l2m,				// left to middle motor
		alarm;				// Alarm
	reg pa,					// Person Approaching
		pp,					// Person Present between door
		mo,					// manual Opening
		r,					// right limit
		m,					// middle limit
		l,					// left limit
		lk,					// lock
		clk,				// clock
		reset;				// reset
	wire[1:0] yt,			// PresentState
			  yt1;			// NextState
	
	//DataFlow Modelling
	/*
	// Calling the main module
	VerilogDM_125_254 f(bt,yt1,r2m,m2r,l2m,m2l,alarm,pa,pp,mo,r,l,m,lk,clk,reset,yt);
	
	// GTKWave Generation for DataFlow Modelling
	initial begin
		$dumpfile("VerilogDM-125-254.vcd");
		$dumpvars(0,Verilog_125_254);
	end
	*/
	
	//Behavorial Modelling
	
	// Calling the main module
	VerilogBM_125_254 f(bt,yt1,r2m,m2r,l2m,m2l,alarm,pa,pp,mo,r,l,m,lk,clk,reset,yt);
	
	// GTKWave Generation for Behavorial Modelling
	initial begin
		$dumpfile("VerilogBM-125-254.vcd");
		$dumpvars(0,Verilog_125_254);
	end
	
	
	// Toggle the input clock after every 10, initial clock set to 1
	initial begin
		clk=1'b1;
		repeat(65)
			#10 clk=~clk;
	end
	
	initial begin
		$display("AUTOMATIC DOOR CONTROLLER\n");
	end

	initial begin
			pa=0;
			pp=0;
			mo=0;
			r=0;
			m=1;
			lk=0;
			l=0;
			reset=1;
		$monitor("Reset=%b both doors closed",reset);
		
		//TestCase1:- Both Doors Closed
		#20;
			pa=0;
			pp=0;
			mo=0;
			r=0;
			m=1;
			lk=0;
			l=0;
			reset=0;
		
		//TestCase2:- Person Approaching
		#20;
			pa=1;
			pp=0;
			mo=0;
			r=0;
			m=0;
			lk=0;
			l=0;
			reset=0;
		$monitor("Person approaching=%b  Door opening=%b",pa,yt);
		//TestCase3:- Person Approaching
		#20;
			pa=1;
			pp=0;
			mo=0;
			r=1;
			m=0;
			lk=0;
			l=1;
			reset=0;
		$monitor("Person approaching=%b  Door opened=%b",pa,yt);
		//TestCase4:- Both Doors open 
		#20;
			pa=0;
			pp=0;
			mo=0;
			r=1;
			m=0;
			lk=0;
			l=1;
			reset=0;
		$monitor("Person approaching=%b  Door closing=%b",pa,yt);
		//TestCase5:- doors closing
		#20;
			pa=0;
			pp=0;
			mo=0;
			r=1;
			m=0;
			lk=0;
			l=1;
		    reset=0;
		
		//TestCase6:- Doors completely closed
		#20;
			pa=0;
			pp=0;
			mo=0;
			r=0;
			m=1;
			lk=0;
			l=0;
		    reset=0;
		$monitor("No external sensor triggered, Door closed=%b",yt);
		//TestCase7:- Doors completely closed
		#20;
			pa=0;
			pp=0;
			mo=0;
			r=0;
			m=1;
			lk=0;
			l=0;
		    reset=0;
		//TestCase8:- Doors completely closed
		#20;
			pa=0;
			pp=0;
			mo=0;
			r=0;
			m=1;
			lk=0;
			l=0;
		    reset=0;
		//TestCase9:- Doors closed and locked
		#20;
			pa=0;
			pp=0;
			mo=0;
			r=0;
			m=1;
			lk=1;
			l=0;
		    reset=0;
		$monitor("Door closed=%b, Door locked=%b",yt,lk);
		//TestCase10:- locked door, tried to open manually(first trial)
		#20;
			pa=0;
			pp=0;
			mo=1;
			r=0;
			m=1;
			lk=1;
			l=0;
		    reset=0;
		$monitor("Door locked=%b, manual open=%b first time, alarm=%b",lk,mo,alarm);
		//TestCase11:- locked door, tried to manually open(first trial)
		#20;
			pa=0;
			pp=0;
			mo=0;
			r=0;
			m=1;
			lk=1;
			l=0;
		    reset=0;
		
		//TestCase12:- locked door
		#20;
			pa=0;
			pp=0;
			mo=1;
			r=0;
			m=1;
			lk=1;
			l=0;
		    reset=0;
		$monitor("Door locked=%b, manual open=%b second time, alarm=%b",lk,mo,alarm);
		//TestCase13:- locked door, tried to manually open(second trial), alarm off
		#20;
			pa=0;
			pp=0;
			mo=0;
			r=0;
			m=1;
			lk=1;
			l=0;
		    reset=0;
		
		//TestCase14:- locked door
		#20;
			pa=0;
			pp=0;
			mo=1;
			r=0;
			m=1;
			lk=1;
			l=0;
		    reset=0;
		$monitor("Door locked=%b, manual open=%b third time, alarm=%b",lk,mo,alarm);
		//TestCase15:- locked door, tried to manually open(third trial), alarm on
		#20;
			pa=0;
			pp=0;
			mo=0;
			r=0;
			m=1;
			lk=1;
			l=0;
		   reset=1;
		$monitor("Reset=%b To stop alarm",reset);
		//TestCase16:- reset=1
		#20;
			pa=0;
			pp=0;
			mo=1;
			r=0;
			m=1;
			lk=0;
			l=0;
		   reset=0;
		$monitor("Door locked=%b, manual open=%b door opening=%b",lk,mo,yt);
		//TestCase17:- Manually opened, door opening
		#20;
			pa=1;
			pp=0;
			mo=0;
			r=1;
			m=0;
			lk=0;
			l=1;
		   reset=0;
		$monitor("Person approaching=%b door opened=%b",pa,yt);
		//TestCase18:- Person approaching, doors remain open
		#20;
			pa=0;
			pp=1;
			mo=0;
			r=1;
			m=0;
			lk=0;
			l=1;
		   reset=0;
		$monitor("Person present=%b door opened=%b",pp,yt);
		//TestCase19:- doors open, person present 
		#20;
			pa=0;
			pp=0;
			mo=0;
			r=1;
			m=0;
			lk=0;
			l=1;
		    reset=0;
		$monitor("No external sensors trigered doors closing=%b",yt);
		//TestCase20:- Doors closing
		#20;
			pa=0;
			pp=0;
			mo=0;
			r=0;
			m=1;
			lk=0;
			l=0;
		    reset=0;
		$monitor("doors fully closed=%b",yt);
		//TestCase21:- doors closed
		#20;
			pa=0;
			pp=0;
			mo=0;
			r=0;
			m=1;
			lk=0;
			l=0;
		   reset=0;
		//TestCase22:- doors closed
		#20;
			pa=1;
			pp=0;
			mo=0;
			r=0;
			m=0;
			lk=0;
			l=0;
		   reset=0;
		$monitor("Person approaching=%b door opening=%b",pa,yt);
		//TestCase23:- Person Approaching, Doors opening
		#20;
			pa=1;
			pp=0;
			mo=0;
			r=1;
			m=0;
			lk=0;
			l=1;
		    reset=0;
		$monitor("Person approaching=%b door opened=%b",pa,yt);
		//TestCase24:- Doors Open
		#20;
			pa=0;
			pp=0;
			mo=0;
			r=1;
			m=0;
			lk=0;
			l=1;
		    reset=0;
		$monitor("No external sensors triggered doors closing=%b",yt);
		//TestCase25:- Doors closing
		#40;
			pa=0;
			pp=0;
			mo=0;
			r=1;
			m=0;
			lk=0;
			l=1;
		    reset=0;
		//TestCase26:- Doors closing
		#40;
			pa=0;
			pp=0;
			mo=0;
			r=0;
			m=0;
			lk=0;
			l=0;
		   reset=0;
		//TestCase27:- Doors closed
		#20;
			pa=0;
			pp=0;
			mo=0;
			r=0;
			m=1;
			lk=0;
			l=0;
		   reset=0;
		$monitor("doors closed=%b",yt);
	end
endmodule

Verilog/VerilogBM-125-254.vcd
$date
	Tue Nov  7 15:23:15 2017
$end
$version
	Icarus Verilog
$end
$timescale
	1ps
$end
$scope module Verilog_125_254 $end
$var wire 1 ! alarm $end
$var wire 1 " bt $end
$var wire 1 # l2m $end
$var wire 1 $ m2l $end
$var wire 1 % m2r $end
$var wire 1 & r2m $end
$var wire 2 ' yt [1:0] $end
$var wire 2 ( yt1 [1:0] $end
$var reg 1 ) clk $end
$var reg 1 * l $end
$var reg 1 + lk $end
$var reg 1 , m $end
$var reg 1 - mo $end
$var reg 1 . pa $end
$var reg 1 / pp $end
$var reg 1 0 r $end
$var reg 1 1 reset $end
$scope module f $end
$var wire 1 2 M $end
$var wire 1 ! alarm $end
$var wire 1 " bt $end
$var wire 1 3 clk $end
$var wire 1 4 l $end
$var wire 1 # l2m $end
$var wire 1 5 lk $end
$var wire 1 $ m2l $end
$var wire 1 % m2r $end
$var wire 1 6 mo $end
$var wire 1 7 pa $end
$var wire 1 8 pp $end
$var wire 1 9 r $end
$var wire 1 & r2m $end
$var wire 1 : reset $end
$var wire 1 ; t1 $end
$var wire 1 < t2 $end
$var wire 2 = yt [1:0] $end
$var wire 2 > yt1 [1:0] $end
$scope module left_door $end
$var wire 1 " bt $end
$var wire 1 3 clk $end
$var wire 1 2 l $end
$var wire 1 % l2r $end
$var wire 1 5 lk $end
$var wire 1 6 mo $end
$var wire 1 7 pa $end
$var wire 1 8 pp $end
$var wire 1 9 r $end
$var wire 1 & r2l $end
$var wire 1 : reset $end
$var wire 2 ? yt [1:0] $end
$var wire 2 @ yt1 [1:0] $end
$scope module f3 $end
$var wire 1 3 clk $end
$var wire 1 2 l $end
$var wire 1 5 lk $end
$var wire 1 6 mo $end
$var wire 1 7 pa $end
$var wire 1 8 pp $end
$var wire 1 9 r $end
$var wire 1 : reset $end
$var reg 2 A yt [1:0] $end
$var reg 2 B yt1 [1:0] $end
$upscope $end
$scope module f4 $end
$var wire 1 3 clk $end
$var wire 1 2 l $end
$var wire 1 5 lk $end
$var wire 1 6 mo $end
$var wire 1 7 pa $end
$var wire 1 8 pp $end
$var wire 1 9 r $end
$var wire 1 : reset $end
$var wire 2 C yt [1:0] $end
$var reg 1 D bt $end
$var reg 1 E l2r $end
$var reg 1 F r2l $end
$upscope $end
$upscope $end
$scope module right_door $end
$var wire 1 " bt $end
$var wire 1 3 clk $end
$var wire 1 2 l $end
$var wire 1 $ l2r $end
$var wire 1 5 lk $end
$var wire 1 6 mo $end
$var wire 1 7 pa $end
$var wire 1 8 pp $end
$var wire 1 4 r $end
$var wire 1 # r2l $end
$var wire 1 : reset $end
$var wire 2 G yt [1:0] $end
$var wire 2 H yt1 [1:0] $end
$scope module f3 $end
$var wire 1 3 clk $end
$var wire 1 2 l $end
$var wire 1 5 lk $end
$var wire 1 6 mo $end
$var wire 1 7 pa $end
$var wire 1 8 pp $end
$var wire 1 4 r $end
$var wire 1 : reset $end
$var reg 2 I yt [1:0] $end
$var reg 2 J yt1 [1:0] $end
$upscope $end
$scope module f4 $end
$var wire 1 3 clk $end
$var wire 1 2 l $end
$var wire 1 5 lk $end
$var wire 1 6 mo $end
$var wire 1 7 pa $end
$var wire 1 8 pp $end
$var wire 1 4 r $end
$var wire 1 : reset $end
$var wire 2 K yt [1:0] $end
$var reg 1 L bt $end
$var reg 1 M l2r $end
$var reg 1 N r2l $end
$upscope $end
$upscope $end
$scope module f7 $end
$var wire 1 6 clk $end
$var wire 1 " enable $end
$var wire 1 : reset $end
$var reg 1 O a0 $end
$var reg 1 P a1 $end
$var reg 1 Q preset $end
$upscope $end
$upscope $end
$upscope $end
$enddefinitions $end
#0
$dumpvars
0Q
0P
0O
0N
0M
0L
b0 K
b0 J
b0 I
b0 H
b0 G
0F
0E
0D
b0 C
b0 B
b0 A
b0 @
b0 ?
b0 >
b0 =
0<
0;
1:
09
08
07
06
05
04
13
12
11
00
0/
0.
0-
1,
0+
0*
1)
b0 (
b0 '
0&
0%
0$
0#
0"
0!
$end
#10000
0)
03
#20000
1)
13
01
0:
#30000
0)
03
#40000
b1 A
b1 I
b1 '
b1 =
b1 ?
b1 C
b1 G
b1 K
b1 B
1E
1%
b1 J
b1 (
b1 >
b1 @
b1 H
1M
1$
1)
13
0,
02
1.
17
#50000
0)
03
#60000
b11 I
b11 A
b11 '
b11 =
b11 ?
b11 C
b11 G
b11 K
0M
0$
b11 J
0E
0%
b11 (
b11 >
b11 @
b11 H
b11 B
1)
13
1*
14
10
19
#70000
0)
03
#80000
b10 A
b10 I
b10 '
b10 =
b10 ?
b10 C
b10 G
b10 K
b10 B
1F
1&
b10 J
b10 (
b10 >
b10 @
b10 H
1N
1#
1)
13
0.
07
#90000
0)
03
#100000
b10 J
b10 B
1)
13
#110000
0)
03
#120000
b0 A
b0 I
b0 '
b0 =
b0 ?
b0 C
b0 G
b0 K
b0 B
0F
0&
b0 (
b0 >
b0 @
b0 H
b0 J
0N
0#
1)
13
0*
04
1,
12
00
09
#130000
0)
03
#140000
1)
13
#150000
0)
03
#160000
1)
13
#170000
0)
03
#180000
1L
b0 J
1D
1"
b0 B
1)
13
1+
15
#190000
0)
03
#200000
1O
1;
b0 B
b0 J
1)
13
1-
16
#210000
0)
03
#220000
b0 J
b0 B
1)
13
0-
06
#230000
0)
03
#240000
1P
1<
0O
0;
b0 B
b0 J
1)
13
1-
16
#250000
0)
03
#260000
b0 J
b0 B
1)
13
0-
06
#270000
0)
03
#280000
1!
1O
1;
b0 B
b0 J
1)
13
1-
16
#290000
0)
03
#300000
0!
0L
0D
0"
0P
0<
0O
0;
1)
13
11
1:
0-
06
#310000
0)
03
#320000
b1 A
b1 I
b1 '
b1 =
b1 ?
b1 C
b1 G
b1 K
b1 B
1E
1%
b1 J
b1 (
b1 >
b1 @
b1 H
1M
1$
1)
13
01
0:
0+
05
1-
16
#330000
0)
03
#340000
b11 I
b11 A
b11 '
b11 =
b11 ?
b11 C
b11 G
b11 K
0M
0$
b11 J
0E
0%
b11 (
b11 >
b11 @
b11 H
b11 B
1)
13
1*
14
0,
02
10
19
0-
06
1.
17
#350000
0)
03
#360000
b11 B
b11 J
1)
13
1/
18
0.
07
#370000
0)
03
#380000
b10 I
b10 A
b10 '
b10 =
b10 ?
b10 C
b10 G
b10 K
1N
1#
b10 J
1F
1&
b10 B
b10 (
b10 >
b10 @
b10 H
1)
13
0/
08
#390000
0)
03
#400000
b0 A
b0 I
b0 '
b0 =
b0 ?
b0 C
b0 G
b0 K
b0 B
0F
0&
b0 (
b0 >
b0 @
b0 H
b0 J
0N
0#
1)
13
0*
04
1,
12
00
09
#410000
0)
03
#420000
1)
13
#430000
0)
03
#440000
b1 A
b1 I
b1 '
b1 =
b1 ?
b1 C
b1 G
b1 K
b1 B
1E
1%
b1 J
b1 (
b1 >
b1 @
b1 H
1M
1$
1)
13
0,
02
1.
17
#450000
0)
03
#460000
b11 I
b11 A
b11 '
b11 =
b11 ?
b11 C
b11 G
b11 K
0M
0$
b11 J
0E
0%
b11 (
b11 >
b11 @
b11 H
b11 B
1)
13
1*
14
10
19
#470000
0)
03
#480000
b10 A
b10 I
b10 '
b10 =
b10 ?
b10 C
b10 G
b10 K
b10 B
1F
1&
b10 J
b10 (
b10 >
b10 @
b10 H
1N
1#
1)
13
0.
07
#490000
0)
03
#500000
b10 J
b10 B
1)
13
#510000
0)
03
#520000
b10 B
b10 J
1)
13
#530000
0)
03
#540000
b10 J
b10 B
1)
13
#550000
0)
03
#560000
b10 B
b10 J
1)
13
0*
04
00
09
#570000
0)
03
#580000
b0 I
b0 A
b0 '
b0 =
b0 ?
b0 C
b0 G
b0 K
0N
0#
b0 J
0F
0&
b0 (
b0 >
b0 @
b0 H
b0 B
1)
13
1,
12
